omniinfer_account/__init__.py
omniinfer_account/account.py
omniinfer_account/config.py
omniinfer_account/data.py
omniinfer_account/error.py
omniinfer_account/system.py
omni_infer_api_account-0.0.11.dist-info/METADATA
omni_infer_api_account-0.0.11.dist-info/WHEEL
omni_infer_api_account-0.0.11.dist-info/top_level.txt
omni_infer_api_account-0.0.11.dist-info/RECORD
