Metadata-Version: 2.1
Name: omni-infer-api-account
Version: 0.0.11
Summary: A secondary distribution account system based on omni infer api.
Home-page: 
Author: stay_miku
Author-email: miku@miku.pics
Requires-Dist: omni-infer-api
